boto3_extensions/__init__.py
boto3_extensions/arn_patch.py
boto3_extensions/data/acm/2015-12-08/arns-1.json
boto3_extensions/data/acm/2015-12-08/resources-1.json
boto3_extensions/data/autoscaling/2011-01-01/arns-1.json
boto3_extensions/data/autoscaling/2011-01-01/resources-1.json
boto3_extensions/data/cloudformation/2010-05-15/arns-1.json
boto3_extensions/data/cloudfront/2017-03-25/arns-1.json
boto3_extensions/data/cloudfront/2017-03-25/resources-1.json
boto3_extensions/data/cloudtrail/2013-11-01/arns-1.json
boto3_extensions/data/cloudtrail/2013-11-01/resources-1.json
boto3_extensions/data/cloudwatch/2010-08-01/arns-1.json
boto3_extensions/data/cognito-identity/2014-06-30/arns-1.json
boto3_extensions/data/cognito-identity/2014-06-30/resources-1.json
boto3_extensions/data/cur/2017-01-06/arns-1.json
boto3_extensions/data/cur/2017-01-06/resources-1.json
boto3_extensions/data/datapipeline/2012-10-29/arns-1.json
boto3_extensions/data/datapipeline/2012-10-29/resources-1.json
boto3_extensions/data/directconnect/2012-10-25/arns-1.json
boto3_extensions/data/directconnect/2012-10-25/resources-1.json
boto3_extensions/data/dynamodb/2012-08-10/arns-1.json
boto3_extensions/data/dynamodb/2012-08-10/resources-1.json
boto3_extensions/data/ec2/2016-11-15/arns-1.json
boto3_extensions/data/ec2/2016-11-15/resources-1.json
boto3_extensions/data/elasticache/2015-02-02/arns-1.json
boto3_extensions/data/elasticache/2015-02-02/resources-1.json
boto3_extensions/data/elb/2012-06-01/arns-1.json
boto3_extensions/data/elb/2012-06-01/resources-1.json
boto3_extensions/data/elbv2/2015-12-01/arns-1.json
boto3_extensions/data/elbv2/2015-12-01/resources-1.json
boto3_extensions/data/emr/2009-03-31/arns-1.json
boto3_extensions/data/emr/2009-03-31/resources-1.json
boto3_extensions/data/forecast/2018-06-26/arns-1.json
boto3_extensions/data/forecast/2018-06-26/resources-1.json
boto3_extensions/data/forecast/2018-06-26/waiters-2.json
boto3_extensions/data/glacier/2012-06-01/arns-1.json
boto3_extensions-0.23.0.dist-info/LICENSE
boto3_extensions-0.23.0.dist-info/METADATA
boto3_extensions-0.23.0.dist-info/WHEEL
boto3_extensions-0.23.0.dist-info/RECORD
