Metadata-Version: 2.1
Name: boto3-extensions
Version: 0.23.0
Summary: Extensions to the AWS SDK for Python
Home-page: https://bitbucket.org/atlassian/boto3_extensions/
License: Apache-2.0
Author: Cloud Engineering
Author-email: cloud-team@atlassian.com
Requires-Python: >=3.8,<4.0
Classifier: License :: OSI Approved :: Apache Software License
Classifier: Programming Language :: Python
Classifier: Programming Language :: Python :: 3
Classifier: Programming Language :: Python :: 3.8
Classifier: Programming Language :: Python :: 3.9
Classifier: Programming Language :: Python :: 3.10
Classifier: Programming Language :: Python :: 3.11
Classifier: Programming Language :: Python :: 3.12
Requires-Dist: boto3 (>=1.17.24)
Requires-Dist: botocore (>=1.20.24)
Project-URL: Documentation, https://bitbucket.org/atlassian/boto3_extensions/
Project-URL: Issues, https://bitbucket.org/atlassian/boto3_extensions/issues
Project-URL: Repository, https://bitbucket.org/atlassian/boto3_extensions/
